adeles/__init__.py
adeles/adele.py
adeles/all.py
adeles/completion.py
adeles/hilbert.py
adeles/idele.py
adeles/matrix.py
adeles/modular.py
adeles/multiplicative_padic.py
adeles/profinite_function.py
adeles/profinite_graph.py
adeles/profinite_integer.py
adeles/profinite_number.py
adeles/ray_class_group.py
adeles/shimura.py
adeles-1.dist-info/LICENSE
adeles-1.dist-info/METADATA
adeles-1.dist-info/WHEEL
adeles-1.dist-info/top_level.txt
adeles-1.dist-info/RECORD
