Metadata-Version: 2.1
Name: adeles
Version: 1
Summary: A SageMath package for computing with adèles and idèles over number fields
Home-page: https://github.com/mathehertogh/adeles
Author: Mathé Hertogh
Author-email: m.c.hertogh@gmail.com
License: GPLv2+
Platform: UNKNOWN
Classifier: Programming Language :: Python :: 3
Classifier: License :: OSI Approved :: GNU General Public License v2 or later (GPLv2+)
Classifier: Operating System :: OS Independent
Classifier: Intended Audience :: Science/Research
Classifier: Topic :: Scientific/Engineering :: Mathematics
Requires-Python: >=3
License-File: LICENSE
